resize_icon/__init__.py
resize_icon/resize.py
resize_icon/spec.py
resize_icon-0.1.3.dist-info/METADATA
resize_icon-0.1.3.dist-info/WHEEL
resize_icon-0.1.3.dist-info/RECORD
