Metadata-Version: 2.1
Name: resize-icon
Version: 0.1.3
Summary: 
Author: yayunHuang
Author-email: yayun146@oursky.com
Requires-Python: >=3.11,<4.0
Classifier: Programming Language :: Python :: 3
Classifier: Programming Language :: Python :: 3.11
Requires-Dist: path (>=16.6.0,<17.0.0)
Requires-Dist: pillow (>=9.1.1,<10.0.0)
